json_comments/__init__.py
json_comments/__init__.pyi
json_comments/json_comments.cpython-312-aarch64-linux-gnu.so
json_comments/py.typed
json_comments-0.1.0.dist-info/METADATA
json_comments-0.1.0.dist-info/WHEEL
json_comments-0.1.0.dist-info/licenses/LICENSE
json_comments-0.1.0.dist-info/RECORD
