Metadata-Version: 2.4
Name: json-comments
Version: 0.1.0
Classifier: Programming Language :: Python :: 3
Classifier: Programming Language :: Rust
Classifier: License :: OSI Approved :: MIT License
Classifier: Operating System :: OS Independent
Classifier: Topic :: Text Processing :: General
Requires-Dist: pytest ; extra == 'dev'
Requires-Dist: commentjson ; extra == 'dev'
Requires-Dist: pyjson5 ; extra == 'dev'
Requires-Dist: msgspec ; extra == 'dev'
Provides-Extra: dev
License-File: LICENSE
Summary: Rust-backed JSON comment and trailing comma stripper
Keywords: json,comments,trailing-commas,rust,performance
Author-email: Tim Hörmann <pypi@audivir.de>
Requires-Python: >=3.7, <3.14
